{"skeleton":{"hash":"rWA4A9eW5Cs","spine":"4.2.43","x":-197,"y":-13.36,"width":394,"height":430.22,"images":"C:/Users/ruben/Documents/Game Dev/Game Jams/Global Game Jam 26/Local Asset Dump/Creature/","audio":"./audio"},"bones":[{"name":"root"},{"name":"Creature","parent":"root","icon":"star"},{"name":"Shadow","parent":"root"},{"name":"Musical Note 1","parent":"root","x":164.44,"y":542.07},{"name":"Musical Note 2","parent":"root","x":298.41,"y":610.06}],"slots":[{"name":"Shadow","bone":"Shadow","attachment":"Small Shadow"},{"name":"root","bone":"Creature","attachment":"root"},{"name":"Musical Note 1","bone":"Musical Note 1"},{"name":"Musical Note 2","bone":"Musical Note 2"},{"name":"Bang","bone":"root"}],"skins":[{"name":"default","attachments":{"Bang":{"Bang":{"x":-152.99,"y":191.15,"width":452,"height":465}},"Musical Note 1":{"Musical Note 1":{"x":1.08,"y":-1.97,"width":54,"height":119}},"Musical Note 2":{"Musical Note 2":{"x":-10.5,"y":-36.49,"width":110,"height":126}},"Shadow":{"Small Shadow":{"x":5.7,"y":6.14,"scaleX":1.3591,"width":197,"height":39}}}},{"name":"Heavy Attack/1","attachments":{"root":{"root":{"name":"H_attack_1","x":0.5,"y":248.12,"width":333,"height":508}}}},{"name":"Heavy Attack/2","attachments":{"root":{"root":{"name":"H_attack_2","y":249.22,"width":342,"height":528}}}},{"name":"Heavy Attack/3","attachments":{"root":{"root":{"name":"H_attack_3","y":331.95,"width":532,"height":714}}}},{"name":"Jumpover/1","attachments":{"root":{"root":{"name":"Jumpover_1","x":0.5,"y":125.14,"width":355,"height":317}}}},{"name":"Jumpover/2","attachments":{"root":{"root":{"name":"Jumpover_2","x":0.5,"y":168.36,"width":375,"height":343}}}},{"name":"Jumpover/3","attachments":{"root":{"root":{"name":"Jumpover_3","y":206.86,"width":394,"height":420}}}},{"name":"Light Attack/1","attachments":{"root":{"root":{"name":"L_attack_1","y":140.86,"width":198,"height":288}}}},{"name":"Light Attack/2","attachments":{"root":{"root":{"name":"L_attack_2","x":-8.83,"y":174.15,"rotation":7.44,"width":204,"height":365}}}},{"name":"Light Attack/3","attachments":{"root":{"root":{"name":"L_attack_3","x":0.5,"y":179.36,"width":171,"height":365}}}}],"animations":{"Attack":{"bones":{"Creature":{"translate":[{"curve":[0.044,0,0.089,0,0.044,77.95,0.089,233.85]},{"time":0.1333,"y":233.85,"curve":[0.178,0,0.222,0,0.178,233.85,0.222,77.95]},{"time":0.2667}],"scale":[{"curve":[0.044,1,0.089,1.212,0.044,1,0.089,1.212]},{"time":0.1333,"x":1.212,"y":1.212,"curve":[0.178,1.212,0.222,1,0.178,1.212,0.222,1]},{"time":0.2667}]}}},"Death":{"slots":{"Bang":{"attachment":[{"name":"Bang"},{"time":0.0667}]},"root":{"alpha":[{"value":1,"curve":[0.089,1,0.178,0]},{"time":0.2667,"value":0}]},"Shadow":{"attachment":[{}]}},"bones":{"Creature":{"rotate":[{"curve":[0.089,0,0.178,-70]},{"time":0.2667,"value":-70}],"translate":[{"curve":[0.107,474.9,0.187,679.5,0.075,417.83,0.187,476.79]},{"time":0.2667,"x":679.5,"y":476.79}],"scale":[{"curve":[0.107,1.915,0.187,1.655,0.107,1.915,0.187,1.655]},{"time":0.2667,"x":1.655,"y":1.655}]}}},"Idle":{"slots":{"Musical Note 1":{"alpha":[{"value":0,"curve":[0.033,0,0.067,1]},{"time":0.1,"value":1,"curve":"stepped"},{"time":0.2667,"value":1},{"time":0.4,"value":0}],"attachment":[{"name":"Musical Note 1"}]},"Musical Note 2":{"alpha":[{"time":0.2,"value":0,"curve":[0.233,0,0.267,1]},{"time":0.3,"value":1,"curve":"stepped"},{"time":0.4667,"value":1},{"time":0.6,"value":0}],"attachment":[{"time":0.2,"name":"Musical Note 2"}]}},"bones":{"Creature":{"scale":[{"curve":[0.099,1,0.201,1,0.099,1,0.201,0.471]},{"time":0.3,"y":0.471,"curve":[0.399,1,0.501,1,0.399,0.471,0.501,1]},{"time":0.6}]},"Musical Note 1":{"translate":[{},{"time":0.4,"x":195.46,"y":187.34}]},"Musical Note 2":{"translate":[{"time":0.2,"x":-136.19,"y":-136.19,"curve":[0.333,-136.19,0.467,93.76,0.333,-136.19,0.467,26.77]},{"time":0.6,"x":93.76,"y":26.77}]}}}}}